{"dynicright":0.600000023841858,"margin":0.0,"time":"2019-02-21 13:39:42","userid":"1301168","username":"yd-jy3"}
{"dynicright":19457.6796875,"margin":0.0,"time":"2019-02-21 13:39:42","userid":"0900888901","username":"gldh-jy1"}
{"dynicright":100.900001525879,"margin":0.0,"time":"2019-02-21 13:39:42","userid":"170895","username":"zdqh-jy2"}
{"dynicright":2603344.5,"margin":542289.9375,"time":"2019-02-21 13:39:42","userid":"101850316","username":"zx-wdf"}
{"dynicright":2032413.5,"margin":361691.0625,"time":"2019-02-21 13:39:42","userid":"170902","username":"zd-zxg"}
{"dynicright":100.669998168945,"margin":0.0,"time":"2019-02-21 13:39:42","userid":"207180189","username":"ya-jy6"}
{"dynicright":1615500.25,"margin":291063.1875,"time":"2019-02-21 13:39:42","userid":"811613","username":"zc-szl"}
{"dynicright":1068978.625,"margin":286767.15625,"time":"2019-02-21 13:39:42","userid":"68806121","username":"xz-qb"}
{"dynicright":2055981.625,"margin":440964.40625,"time":"2019-02-21 13:39:42","userid":"92000673","username":"dadi-lzy"}
{"dynicright":1218072.0,"margin":371877.5625,"time":"2019-02-21 13:39:42","userid":"87900075","username":"ht-pbs"}
{"dynicright":114.529998779297,"margin":0.0,"time":"2019-02-21 13:39:42","userid":"23600059","username":"zs-lpc"}
{"dynicright":2006657.125,"margin":333016.8125,"time":"2019-02-21 13:39:43","userid":"23600133","username":"zs-snn"}
{"dynicright":101.650001525879,"margin":0.0,"time":"2019-02-21 13:39:44","userid":"23600205","username":"zs-lff"}
{"dynicright":1564267.25,"margin":517098.1875,"time":"2019-02-21 13:39:44","userid":"23600198","username":"zs-xwy"}
{"dynicright":1218642.0,"margin":371877.5625,"time":"2019-02-21 13:40:11","userid":"87900075","username":"ht-pbs"}
{"dynicright":1070068.625,"margin":286767.15625,"time":"2019-02-21 13:40:11","userid":"68806121","username":"xz-qb"}
{"dynicright":100.669998168945,"margin":0.0,"time":"2019-02-21 13:40:11","userid":"207180189","username":"ya-jy6"}
{"dynicright":19457.6796875,"margin":0.0,"time":"2019-02-21 13:40:11","userid":"0900888901","username":"gldh-jy1"}
{"dynicright":1615720.25,"margin":291063.1875,"time":"2019-02-21 13:40:11","userid":"811613","username":"zc-szl"}
{"dynicright":100.900001525879,"margin":0.0,"time":"2019-02-21 13:40:11","userid":"170895","username":"zdqh-jy2"}
{"dynicright":0.600000023841858,"margin":0.0,"time":"2019-02-21 13:40:11","userid":"1301168","username":"yd-jy3"}
{"dynicright":2033078.5,"margin":361691.0625,"time":"2019-02-21 13:40:11","userid":"170902","username":"zd-zxg"}
{"dynicright":2605104.5,"margin":542289.9375,"time":"2019-02-21 13:40:11","userid":"101850316","username":"zx-wdf"}
{"dynicright":2056086.625,"margin":440964.40625,"time":"2019-02-21 13:40:11","userid":"92000673","username":"dadi-lzy"}
{"dynicright":101.650001525879,"margin":0.0,"time":"2019-02-21 13:40:11","userid":"23600205","username":"zs-lff"}
{"dynicright":114.529998779297,"margin":0.0,"time":"2019-02-21 13:40:11","userid":"23600059","username":"zs-lpc"}
{"dynicright":1564627.25,"margin":517098.1875,"time":"2019-02-21 13:40:11","userid":"23600198","username":"zs-xwy"}
{"dynicright":2007017.125,"margin":333016.8125,"time":"2019-02-21 13:40:11","userid":"23600133","username":"zs-snn"}
{"dynicright":1218337.0,"margin":371877.5625,"time":"2019-02-21 13:40:41","userid":"87900075","username":"ht-pbs"}
{"dynicright":1069183.625,"margin":286767.15625,"time":"2019-02-21 13:40:41","userid":"68806121","username":"xz-qb"}
{"dynicright":1615530.25,"margin":291063.1875,"time":"2019-02-21 13:40:41","userid":"811613","username":"zc-szl"}
{"dynicright":2603579.5,"margin":542289.9375,"time":"2019-02-21 13:40:41","userid":"101850316","username":"zx-wdf"}
{"dynicright":100.900001525879,"margin":0.0,"time":"2019-02-21 13:40:41","userid":"170895","username":"zdqh-jy2"}
{"dynicright":2032633.5,"margin":361691.0625,"time":"2019-02-21 13:40:41","userid":"170902","username":"zd-zxg"}
{"dynicright":19457.6796875,"margin":0.0,"time":"2019-02-21 13:40:41","userid":"0900888901","username":"gldh-jy1"}
{"dynicright":100.669998168945,"margin":0.0,"time":"2019-02-21 13:40:41","userid":"207180189","username":"ya-jy6"}
{"dynicright":0.600000023841858,"margin":0.0,"time":"2019-02-21 13:40:41","userid":"1301168","username":"yd-jy3"}
{"dynicright":2055606.625,"margin":440964.40625,"time":"2019-02-21 13:40:41","userid":"92000673","username":"dadi-lzy"}
{"dynicright":114.529998779297,"margin":0.0,"time":"2019-02-21 13:40:41","userid":"23600059","username":"zs-lpc"}
{"dynicright":101.650001525879,"margin":0.0,"time":"2019-02-21 13:40:41","userid":"23600205","username":"zs-lff"}
{"dynicright":2006912.125,"margin":333016.8125,"time":"2019-02-21 13:40:41","userid":"23600133","username":"zs-snn"}
{"dynicright":1564522.25,"margin":517098.1875,"time":"2019-02-21 13:40:41","userid":"23600198","username":"zs-xwy"}
{"dynicright":2603504.5,"margin":542289.9375,"time":"2019-02-21 13:41:24","userid":"101850316","username":"zx-wdf"}
{"dynicright":19457.6796875,"margin":0.0,"time":"2019-02-21 13:41:24","userid":"0900888901","username":"gldh-jy1"}
{"dynicright":100.900001525879,"margin":0.0,"time":"2019-02-21 13:41:24","userid":"170895","username":"zdqh-jy2"}
{"dynicright":0.600000023841858,"margin":0.0,"time":"2019-02-21 13:41:24","userid":"1301168","username":"yd-jy3"}
{"dynicright":2032418.5,"margin":361691.0625,"time":"2019-02-21 13:41:24","userid":"170902","username":"zd-zxg"}
{"dynicright":100.669998168945,"margin":0.0,"time":"2019-02-21 13:41:24","userid":"207180189","username":"ya-jy6"}
{"dynicright":1616070.25,"margin":291063.1875,"time":"2019-02-21 13:41:24","userid":"811613","username":"zc-szl"}
{"dynicright":1069433.625,"margin":286767.15625,"time":"2019-02-21 13:41:24","userid":"68806121","username":"xz-qb"}
{"dynicright":2056426.625,"margin":440964.40625,"time":"2019-02-21 13:41:24","userid":"92000673","username":"dadi-lzy"}
{"dynicright":1218542.0,"margin":371877.5625,"time":"2019-02-21 13:41:24","userid":"87900075","username":"ht-pbs"}
{"dynicright":114.529998779297,"margin":0.0,"time":"2019-02-21 13:41:25","userid":"23600059","username":"zs-lpc"}
{"dynicright":1564857.25,"margin":517098.1875,"time":"2019-02-21 13:41:25","userid":"23600198","username":"zs-xwy"}
{"dynicright":2007167.125,"margin":333016.8125,"time":"2019-02-21 13:41:26","userid":"23600133","username":"zs-snn"}
{"dynicright":101.650001525879,"margin":0.0,"time":"2019-02-21 13:41:26","userid":"23600205","username":"zs-lff"}
